<?xml version="1.0" encoding="UTF-8"?>
<GenRun Id="synth_1" LaunchPart="xc7a35tcpg236-1" LaunchTime="1648207447">
  <File Type="PA-TCL" Name="adc.tcl"/>
  <File Type="RDS-PROPCONSTRS" Name="adc_drc_synth.rpt"/>
  <File Type="REPORTS-TCL" Name="adc_reports.tcl"/>
  <File Type="RDS-RDS" Name="adc.vds"/>
  <File Type="RDS-UTIL" Name="adc_utilization_synth.rpt"/>
  <File Type="RDS-UTIL-PB" Name="adc_utilization_synth.pb"/>
  <File Type="RDS-DCP" Name="adc.dcp"/>
  <File Type="VDS-TIMINGSUMMARY" Name="adc_timing_summary_synth.rpt"/>
  <File Type="VDS-TIMING-PB" Name="adc_timing_summary_synth.pb"/>
  <FileSet Name="sources" Type="DesignSrcs" RelSrcDir="$PSRCDIR/sources_1" RelGenDir="$PGENDIR/sources_1">
    <Filter Type="Srcs"/>
    <File Path="$PSRCDIR/sources_1/imports/hdl/XADCdemo.v">
      <FileInfo>
        <Attr Name="UserDisabled" Val="1"/>
        <Attr Name="ImportPath" Val="$PPRDIR/../../../OneDrive - Danmarks Tekniske Universitet/Dokumenter/GitHub/g/GitHub/src/hdl/XADCdemo.v"/>
        <Attr Name="ImportTime" Val="1645791308"/>
        <Attr Name="UsedIn" Val="synthesis"/>
        <Attr Name="UsedIn" Val="implementation"/>
        <Attr Name="UsedIn" Val="simulation"/>
      </FileInfo>
    </File>
    <File Path="$PSRCDIR/sources_1/new/XADC written with VHDL.vhd">
      <FileInfo>
        <Attr Name="UsedIn" Val="synthesis"/>
        <Attr Name="UsedIn" Val="simulation"/>
      </FileInfo>
    </File>
    <File Path="$PPRDIR/../XADC.v">
      <FileInfo>
        <Attr Name="UserDisabled" Val="1"/>
        <Attr Name="UsedIn" Val="synthesis"/>
        <Attr Name="UsedIn" Val="implementation"/>
        <Attr Name="UsedIn" Val="simulation"/>
      </FileInfo>
    </File>
    <Config>
      <Option Name="DesignMode" Val="RTL"/>
      <Option Name="TopModule" Val="adc"/>
    </Config>
  </FileSet>
  <FileSet Name="constrs_in" Type="Constrs" RelSrcDir="$PSRCDIR/constrs_1">
    <Filter Type="Constrs"/>
    <File Path="$PSRCDIR/constrs_1/imports/vending/vending.xdc">
      <FileInfo>
        <Attr Name="ImportPath" Val="$PPRDIR/../../../OneDrive - Danmarks Tekniske Universitet/Dokumenter/DE2/chisel-lab/vending/vending.xdc"/>
        <Attr Name="ImportTime" Val="1618500701"/>
        <Attr Name="UsedIn" Val="synthesis"/>
        <Attr Name="UsedIn" Val="implementation"/>
      </FileInfo>
    </File>
    <Config>
      <Option Name="TargetConstrsFile" Val="$PSRCDIR/constrs_1/imports/vending/vending.xdc"/>
      <Option Name="ConstrsType" Val="XDC"/>
    </Config>
  </FileSet>
  <FileSet Name="utils" Type="Utils" RelSrcDir="$PSRCDIR/utils_1">
    <Filter Type="Utils"/>
    <Config>
      <Option Name="TopAutoSet" Val="TRUE"/>
    </Config>
  </FileSet>
  <Strategy Version="1" Minor="2">
    <StratHandle Name="Vivado Synthesis Defaults" Flow="Vivado Synthesis 2020"/>
    <Step Id="synth_design"/>
  </Strategy>
  <BlockFileSet Type="BlockSrcs" Name="xadc_wiz_0"/>
</GenRun>
